sastools/__init__.py
sastools/_version.py
sastools/wavelet_transform.py
sastools/analyzer/__init__.py
sastools/analyzer/curvefitting.py
sastools/analyzer/enums.py
sastools/analyzer/llcphase.py
sastools/analyzer/llcphases.py
sastools/analyzer/sansanalyzers.py
sastools/analyzer/saxsanalyzers.py
sastools/readers/__init__.py
sastools/readers/infer_type.py
sastools/readers/originreader.py
sastools/readers/pdhreader.py
sastools/readers/seriesreader.py
SAS_tools-1.1.2.dist-info/LICENSE
SAS_tools-1.1.2.dist-info/METADATA
SAS_tools-1.1.2.dist-info/WHEEL
SAS_tools-1.1.2.dist-info/top_level.txt
SAS_tools-1.1.2.dist-info/RECORD
