Metadata-Version: 2.1
Name: SAS-tools
Version: 1.1.2
Summary: SAS-tools contains useful functions and classes for working with SAS data.
Author-email: Torsten Giess <torsten.giess@ibtb.uni-stuttgart.de>, Selina Itzigehl <selina.itzigehl@ipc.uni-stuttgart.de>, Jan Range <jan.range@simtech.uni-stuttgart.de>, Richard Schoemig <richard.schoemig@ibtb.uni-stuttgart.de>
Maintainer-email: FAIR Chemistry <fairchemistry@ibtb.uni-stuttgart.de>
License: MIT License        
Project-URL: Homepage, https://github.com/FAIRChemistry
Project-URL: Repository, https://github.com/FAIRChemistry/SAS-tools
Keywords: RDM,SAS,SAXS
Classifier: Development Status :: 5 - Production/Stable
Classifier: Programming Language :: Python :: 3
Classifier: Programming Language :: Python :: 3 :: Only
Classifier: Programming Language :: Python :: 3.10
Classifier: Topic :: Scientific/Engineering :: Chemistry
Requires-Python: >=3.7
License-File: LICENSE
Requires-Dist: lmfit
Requires-Dist: lxml
Requires-Dist: matplotlib
Requires-Dist: numpy
Requires-Dist: pandas
Requires-Dist: pyAnIML (==1.0.2)
Requires-Dist: seaborn
Requires-Dist: scipy
Requires-Dist: pytest (>=7.2.0)
